fitfile/__init__.py
fitfile/activity_fields.py
fitfile/base_type.py
fitfile/data.py
fitfile/data_field.py
fitfile/data_message.py
fitfile/definition_message.py
fitfile/definition_message_data.py
fitfile/dev_data_field.py
fitfile/dev_field.py
fitfile/developer_field_definition.py
fitfile/device_enums.py
fitfile/device_fields.py
fitfile/enum_fields.py
fitfile/field_definition.py
fitfile/field_value.py
fitfile/fields.py
fitfile/file.py
fitfile/file_header.py
fitfile/file_type.py
fitfile/manufacturer.py
fitfile/manufacturer_product_fields.py
fitfile/measurement.py
fitfile/message_type.py
fitfile/object_fields.py
fitfile/product.py
fitfile/record_fields.py
fitfile/record_header.py
fitfile/sport.py
fitfile/type_fields.py
fitfile/units.py
fitfile/user_fields.py
fitfile/version_info.py
fitfile/conversions/__init__.py
fitfile/conversions/conversions.py
fitfile/exceptions/__init__.py
fitfile/exceptions/exceptions.py
fitfile/field_enums/__init__.py
fitfile/field_enums/field_enums.py
fitfile-1.1.11.dist-info/licenses/LICENSE
fitfile-1.1.11.dist-info/METADATA
fitfile-1.1.11.dist-info/WHEEL
fitfile-1.1.11.dist-info/top_level.txt
fitfile-1.1.11.dist-info/RECORD
